<layouts>
    <width>800</width>
    <height>600</height>
    <layout>
        <name>deck01</name>
        <x>675</x>
        <y>200</y>
        <width>100</width>
        <height>100</height>
        </layout><layout>
        <name>deck02</name>
        <x>675</x>
        <y>300</y>
        <width>100</width>
        <height>100</height>
        </layout><layout>
        <name>deck03</name>
        <x>675</x>
        <y>400</y>
        <width>100</width>
        <height>100</height>
        </layout><layout>
        <name>save</name>
        <x>675</x>
        <y>525</y>
        <width>100</width>
        <height>25</height>
        </layout><layout>
        <name>nowCost</name>
        <x>675</x>
        <y>25</y>
        <width>100</width>
        <height>100</height>
        </layout><layout>
        <name>deckLabel</name>
        <x>675</x>
        <y>175</y>
        <width>100</width>
        <height>25</height>
        </layout><layout>
        <name>hitPoint</name>
        <x>25</x>
        <y>50</y>
        <width>100</width>
        <height>25</height>
        </layout><layout>
        <name>attackPoint</name>
        <x>25</x>
        <y>100</y>
        <width>100</width>
        <height>25</height>
        </layout><layout>
        <name>defencePoint</name>
        <x>25</x>
        <y>150</y>
        <width>100</width>
        <height>25</height>
        </layout><layout>
        <name>moveRangePoint</name>
        <x>25</x>
        <y>200</y>
        <width>100</width>
        <height>25</height>
        </layout><layout>
        <name>attackRangePoint</name>
        <x>25</x>
        <y>250</y>
        <width>100</width>
        <height>25</height>
        </layout><layout>
        <name>cost</name>
        <x>25</x>
        <y>300</y>
        <width>100</width>
        <height>25</height>
        </layout><layout>
        <name>heroes</name>
        <x>175</x>
        <y>50</y>
        <width>450</width>
        <height>150</height>
        </layout><layout>
        <name>playersLabel</name>
        <x>304</x>
        <y>225</y>
        <width>200</width>
        <height>25</height>
        </layout><layout>
        <name>heroesLabel</name>
        <x>300</x>
        <y>25</y>
        <width>200</width>
        <height>25</height>
        </layout><layout>
        <name>players</name>
        <x>175</x>
        <y>250</y>
        <width>450</width>
        <height>300</height>
        </layout>
    </layouts>